LICENSE.txt
MANIFEST.in
README.txt
setup.cfg
setup.py
doc/Makefile
doc/rest/conf.py
doc/rest/contents.rst
doc/rest/guidelist.rst
doc/rest/sequences.rst
doc/rest/team.rst
doc/rest/whatsnew.rst
doc/rest/guides/devguide.rst
doc/rest/guides/libnclist.rst
doc/rest/guides/testing.rst
doc/rest/recipes/alignment_recipes.rst
doc/rest/reference/annotation.rst
doc/rest/reference/blast.rst
doc/rest/reference/classutil.rst
doc/rest/reference/cnestedlist.rst
doc/rest/reference/coordinator.rst
doc/rest/reference/downloader.rst
doc/rest/reference/mapping.rst
doc/rest/reference/metabase.rst
doc/rest/reference/seqdb.rst
doc/rest/reference/sequence.rst
doc/rest/reference/sequtil.rst
doc/rest/reference/sqlgraph.rst
doc/rest/reference/worldbase.rst
doc/rest/static/contents.png
doc/rest/static/data-browser.png
doc/rest/static/pygr-doc.css
doc/rest/static/pygr-epydoc.css
doc/rest/static/pygr-logo.gif
doc/rest/templates/index.html
doc/rest/templates/indexsidebar.html
doc/rest/templates/layout.html
doc/rest/templates/media.html
doc/rest/tutorials/alignment.rst
doc/rest/tutorials/annotating-yeast.rst
doc/rest/tutorials/annotation.rst
doc/rest/tutorials/annotation2.rst
doc/rest/tutorials/compgenomics.rst
doc/rest/tutorials/db.rst
doc/rest/tutorials/db_basic.rst
doc/rest/tutorials/develop.rst
doc/rest/tutorials/gene.rst
doc/rest/tutorials/graphquery.rst
doc/rest/tutorials/sequence.rst
doc/rest/tutorials/slice_pickle_obj.py
doc/rest/tutorials/ucsc_ensembl.rst
doc/rest/tutorials/worldbase.rst
doc/rest/tutorials/worldbase2.rst
doc/rest/tutorials/xmlrpc.rst
misc/pygrrc.example
misc/debian/changelog
misc/debian/compat
misc/debian/control
misc/debian/copyright
misc/debian/pycompat
misc/debian/rules
misc/debian/watch
misc/fink/pygr-doc.info
misc/fink/pygr-py.info
misc/portage/pygr-9999.ebuild
misc/portage/pygr-VER.ebuild
pygr/Data.py
pygr/Makefile
pygr/__init__.py
pygr/annotation.py
pygr/blast.py
pygr/cdict.c
pygr/cdict.pxd
pygr/cdict.pyx
pygr/cgraph.c
pygr/cgraph.h
pygr/classutil.py
pygr.egg-info/PKG-INFO
pygr.egg-info/SOURCES.txt
pygr.egg-info/dependency_links.txt
pygr.egg-info/top_level.txt
