Metadata-Version: 1.0
Name: pygr
Version: 0.8.2
Summary: Pygr, a Python graph-database toolkit oriented primarily on bioinformatics
Home-page: http://code.google.com/p/pygr/
Author: Christopher Lee
Author-email: leec@chem.ucla.edu
License: New BSD License
Platform: UNKNOWN
Classifier: Development Status :: 5 - Production/Stable
Classifier: Operating System :: MacOS :: MacOS X
Classifier: Operating System :: Microsoft :: Windows :: Windows NT/2000
Classifier: Operating System :: OS Independent
Classifier: Operating System :: POSIX
Classifier: Operating System :: POSIX :: Linux
Classifier: Operating System :: Unix
Classifier: Programming Language :: Python
Classifier: Topic :: Scientific/Engineering
Classifier: Topic :: Scientific/Engineering :: Bio-Informatics
